py_subtitle_extractor/__init__.py
py_subtitle_extractor/__main__.py
py_subtitle_extractor/ebml.py
py_subtitle_extractor/main.py
py_subtitle_extractor/mkv.py
py_subtitle_extractor/srt.py
py_subtitle_extractor-1.0.5.dist-info/licenses/LICENSE
py_subtitle_extractor-1.0.5.dist-info/METADATA
py_subtitle_extractor-1.0.5.dist-info/WHEEL
py_subtitle_extractor-1.0.5.dist-info/top_level.txt
py_subtitle_extractor-1.0.5.dist-info/RECORD
