Metadata-Version: 2.4
Name: py_subtitle_extractor
Version: 1.0.5
Summary: Pure-Python MKV subtitle extractor
Author-email: Re999 <dariusz23@gmail.com>
License: MIT
Classifier: Programming Language :: Python :: 3
Classifier: License :: OSI Approved :: MIT License
Classifier: Operating System :: OS Independent
Requires-Python: >=3.8
License-File: LICENSE
Dynamic: license-file
